spins/__init__.py
spins/fdfd_solvers/__init__.py
spins/fdfd_solvers/dipole.py
spins/fdfd_solvers/local_matrix_solvers.py
spins/fdfd_solvers/maxwell.py
spins/fdfd_solvers/phc_mode_solver.py
spins/fdfd_solvers/waveguide_mode.py
spins/fdfd_tools/__init__.py
spins/fdfd_tools/free_space_sources.py
spins/fdfd_tools/functional.py
spins/fdfd_tools/grid.py
spins/fdfd_tools/operators.py
spins/fdfd_tools/solvers.py
spins/fdfd_tools/test_grid.py
spins/fdfd_tools/types.py
spins/fdfd_tools/vectorization.py
spins/fdfd_tools/waveguide.py
spins/fdfd_tools/waveguide_mode.py
spins/gds/__init__.py
spins/gds/gen_gds.py
spins/gds/parse_gds.py
spins/gds/test_parse_gds.py
spins/goos/__init__.py
spins/goos/array.py
spins/goos/common_schemas.py
spins/goos/compat.py
spins/goos/flows.py
spins/goos/generic.py
spins/goos/graph_executor.py
spins/goos/grating.py
spins/goos/material.py
spins/goos/math.py
spins/goos/optimize.py
spins/goos/schema_registry.py
spins/goos/shapes.py
spins/goos/test_array.py
spins/goos/test_flows.py
spins/goos/test_generic.py
spins/goos/test_graph_executor.py
spins/goos/test_grating.py
spins/goos/test_math.py
spins/goos/test_optimize.py
spins/goos/test_shapes.py
spins/goos/util.py
spins/goos/extra/__init__.py
spins/goos/optplan/__init__.py
spins/goos/optplan/context.py
spins/goos/optplan/optplan.py
spins/goos/optplan/schema.py
spins/goos/optplan/schema_optplan.py
spins/goos/optplan/schema_types.py
spins/goos/optplan/schema_utils.py
spins/goos/optplan/test_optplan.py
spins/goos/optplan/test_schema.py
spins/goos/optplan/test_schema_types.py
spins/goos_sim/__init__.py
spins/goos_sim/maxwell/__init__.py
spins/goos_sim/maxwell/render.py
spins/goos_sim/maxwell/simspace.py
spins/goos_sim/maxwell/simulate.py
spins/goos_sim/maxwell/test_render.py
spins/goos_sim/maxwell/test_simulate.py
spins/gridlock/__init__.py
spins/gridlock/_helpers.py
spins/gridlock/direction.py
spins/gridlock/error.py
spins/gridlock/float_raster.py
spins/gridlock/grid.py
spins/gridlock/grid_type.py
spins-0.2.0.dist-info/LICENSE
spins-0.2.0.dist-info/METADATA
spins-0.2.0.dist-info/WHEEL
spins-0.2.0.dist-info/top_level.txt
spins-0.2.0.dist-info/RECORD
